{
	"type" : "FeatureCollection",
	"name" : "data",
	"features" : [
		{
			"type" : "Feature",
			"geometry" : {
				"type" : "Point",
				"coordinates" : [ 7.628, 51.96 ]
			},
			"properties" : {
				"id" : 1,
				"module" : "Water quality",
				"site" : "Munster Stadt",
				"gis_image_url" : "https://raw.githubusercontent.com/UpekshaIndeewari/ABCD/main/image.png",
				"x_coordinate" : 7.628,
				"y_coordinate" : 51.96
			}
		},
		{
			"type" : "Feature",
			"geometry" : {
				"type" : "Point",
				"coordinates" : [ 8.807, 53.083 ]
			},
			"properties" : {
				"id" : 2,
				"module" : "Landcover change",
				"site" : "Bremen University",
				"gis_image_url" : "https://raw.githubusercontent.com/UpekshaIndeewari/ABCD/main/image2.png",
				"x_coordinate" : 8.807,
				"y_coordinate" : 53.083
			}
		},
		{
			"type" : "Feature",
			"geometry" : {
				"type" : "Point",
				"coordinates" : [ 9.993, 53.551 ]
			},
			"properties" : {
				"id" : 3,
				"module" : "Coastal change",
				"site" : "Hamburg Port",
				"gis_image_url" : "https://raw.githubusercontent.com/UpekshaIndeewari/ABCD/main/image2.png",
				"x_coordinate" : 9.993,
				"y_coordinate" : 53.551
			}
		},
		{
			"type" : "Feature",
			"geometry" : {
				"type" : "Point",
				"coordinates" : [ 10.139, 54.322 ]
			},
			"properties" : {
				"id" : 4,
				"module" : "Coastal vulnerability",
				"site" : "Kiel Bay",
				"gis_image_url" : "https://raw.githubusercontent.com/UpekshaIndeewari/ABCD/main/images3.png",
				"x_coordinate" : 10.139,
				"y_coordinate" : 54.322
			}
		},
		{
			"type" : "Feature",
			"geometry" : {
				"type" : "Point",
				"coordinates" : [ 9.466, 47.661 ]
			},
			"properties" : {
				"id" : 5,
				"module" : "Water quality",
				"site" : "Lake Constance",
				"gis_image_url" : "https://raw.githubusercontent.com/UpekshaIndeewari/ABCD/main/image.png",
				"x_coordinate" : 9.466,
				"y_coordinate" : 47.661
			}
		},
		{
			"type" : "Feature",
			"geometry" : {
				"type" : "Point",
				"coordinates" : [ 12.373, 51.339 ]
			},
			"properties" : {
				"id" : 6,
				"module" : "Landcover change",
				"site" : "Leipzig Forest",
				"gis_image_url" : "https://raw.githubusercontent.com/UpekshaIndeewari/ABCD/main/image.png",
				"x_coordinate" : 12.373,
				"y_coordinate" : 51.339
			}
		},
		{
			"type" : "Feature",
			"geometry" : {
				"type" : "Point",
				"coordinates" : [ 12.14, 54.088 ]
			},
			"properties" : {
				"id" : 7,
				"module" : "Coastal change",
				"site" : "Rostock Harbor",
				"gis_image_url" : "https://raw.githubusercontent.com/UpekshaIndeewari/ABCD/main/analytic_black.png",
				"x_coordinate" : 12.14,
				"y_coordinate" : 54.088
			}
		},
		{
			"type" : "Feature",
			"geometry" : {
				"type" : "Point",
				"coordinates" : [ 9.433, 54.784 ]
			},
			"properties" : {
				"id" : 8,
				"module" : "Coastal vulnerability",
				"site" : "Flensburg Coast",
				"gis_image_url" : "https://raw.githubusercontent.com/UpekshaIndeewari/ABCD/main/analytic_black.png",
				"x_coordinate" : 9.433,
				"y_coordinate" : 54.784
			}
		},
		{
			"type" : "Feature",
			"geometry" : {
				"type" : "Point",
				"coordinates" : [ 9.738, 52.374 ]
			},
			"properties" : {
				"id" : 9,
				"module" : "Water quality",
				"site" : "Hannover Riverbank",
				"gis_image_url" : "https://raw.githubusercontent.com/UpekshaIndeewari/ABCD/main/analytic_black.png",
				"x_coordinate" : 9.738,
				"y_coordinate" : 52.374
			}
		},
		{
			"type" : "Feature",
			"geometry" : {
				"type" : "Point",
				"coordinates" : [ 13.405, 52.52 ]
			},
			"properties" : {
				"id" : 10,
				"module" : "Landcover change",
				"site" : "Berlin City Park",
				"gis_image_url" : "https://raw.githubusercontent.com/UpekshaIndeewari/ABCD/main/analytic_black.png",
				"x_coordinate" : 13.405,
				"y_coordinate" : 52.52
			}
		},
		{
			"type" : "Feature",
			"geometry" : {
				"type" : "Point",
				"coordinates" : [ 13.388, 54.093 ]
			},
			"properties" : {
				"id" : 11,
				"module" : "Coastal change",
				"site" : "Greifswald Shore",
				"gis_image_url" : "https://raw.githubusercontent.com/UpekshaIndeewari/ABCD/main/analytic_black.png",
				"x_coordinate" : 13.388,
				"y_coordinate" : 54.093
			}
		},
		{
			"type" : "Feature",
			"geometry" : {
				"type" : "Point",
				"coordinates" : [ 10.687, 53.868 ]
			},
			"properties" : {
				"id" : 12,
				"module" : "Coastal vulnerability",
				"site" : "Lübeck Bay",
				"gis_image_url" : "https://raw.githubusercontent.com/UpekshaIndeewari/ABCD/main/analytic_black.png",
				"x_coordinate" : 10.687,
				"y_coordinate" : 53.868
			}
		},
		{
			"type" : "Feature",
			"geometry" : {
				"type" : "Point",
				"coordinates" : [ 6.96, 50.937 ]
			},
			"properties" : {
				"id" : 13,
				"module" : "Water quality",
				"site" : "Cologne Rhine",
				"gis_image_url" : "https://raw.githubusercontent.com/UpekshaIndeewari/ABCD/main/analytic_black.png",
				"x_coordinate" : 6.96,
				"y_coordinate" : 50.937
			}
		},
		{
			"type" : "Feature",
			"geometry" : {
				"type" : "Point",
				"coordinates" : [ 7.852, 47.995 ]
			},
			"properties" : {
				"id" : 14,
				"module" : "Landcover change",
				"site" : "Freiburg Valley",
				"gis_image_url" : "https://raw.githubusercontent.com/UpekshaIndeewari/ABCD/main/analytic_black.png",
				"x_coordinate" : 7.852,
				"y_coordinate" : 47.995
			}
		},
		{
			"type" : "Feature",
			"geometry" : {
				"type" : "Point",
				"coordinates" : [ 8.697, 53.867 ]
			},
			"properties" : {
				"id" : 15,
				"module" : "Coastal change",
				"site" : "Cuxhaven Beach",
				"gis_image_url" : "https://raw.githubusercontent.com/UpekshaIndeewari/ABCD/main/analytic_black.png",
				"x_coordinate" : 8.697,
				"y_coordinate" : 53.867
			}
		},
		{
			"type" : "Feature",
			"geometry" : {
				"type" : "Point",
				"coordinates" : [ 8.112, 53.529 ]
			},
			"properties" : {
				"id" : 16,
				"module" : "Coastal vulnerability",
				"site" : "Wilhelmshaven",
				"gis_image_url" : "https://raw.githubusercontent.com/UpekshaIndeewari/ABCD/main/analytic_black.png",
				"x_coordinate" : 8.112,
				"y_coordinate" : 53.529
			}
		},
		{
			"type" : "Feature",
			"geometry" : {
				"type" : "Point",
				"coordinates" : [ 13.737, 51.05 ]
			},
			"properties" : {
				"id" : 17,
				"module" : "Water quality",
				"site" : "Dresden Elbe",
				"gis_image_url" : "https://raw.githubusercontent.com/UpekshaIndeewari/ABCD/main/analytic_black.png",
				"x_coordinate" : 13.737,
				"y_coordinate" : 51.05
			}
		},
		{
			"type" : "Feature",
			"geometry" : {
				"type" : "Point",
				"coordinates" : [ 11.029, 50.984 ]
			},
			"properties" : {
				"id" : 18,
				"module" : "Landcover change",
				"site" : "Erfurt Field",
				"gis_image_url" : "https://raw.githubusercontent.com/UpekshaIndeewari/ABCD/main/analytic_black.png",
				"x_coordinate" : 11.029,
				"y_coordinate" : 50.984
			}
		},
		{
			"type" : "Feature",
			"geometry" : {
				"type" : "Point",
				"coordinates" : [ 13.082, 54.309 ]
			},
			"properties" : {
				"id" : 19,
				"module" : "Coastal change",
				"site" : "Stralsund Coast",
				"gis_image_url" : "https://raw.githubusercontent.com/UpekshaIndeewari/ABCD/main/analytic_black.png",
				"x_coordinate" : 13.082,
				"y_coordinate" : 54.309
			}
		},
		{
			"type" : "Feature",
			"geometry" : {
				"type" : "Point",
				"coordinates" : [ 7.206, 53.367 ]
			},
			"properties" : {
				"id" : 20,
				"module" : "Coastal vulnerability",
				"site" : "Emden Bay",
				"gis_image_url" : "https://raw.githubusercontent.com/UpekshaIndeewari/ABCD/main/analytic_black.png",
				"x_coordinate" : 7.206,
				"y_coordinate" : 53.367
			}
		}
	]
}